AUTHORS.rst
CONTRIBUTING.rst
LICENSE
MANIFEST.in
README.rst
dev-requirements.txt
requirements.txt
setup.cfg
setup.py
versioneer.py
adviewer/__init__.py
adviewer/_version.py
adviewer/data_model.py
adviewer/device_model.py
adviewer/discovery.py
adviewer/graph.py
adviewer/image_viewer.ui
adviewer/main.py
adviewer/temp.py
adviewer/utils.py
adviewer.egg-info/PKG-INFO
adviewer.egg-info/SOURCES.txt
adviewer.egg-info/dependency_links.txt
adviewer.egg-info/entry_points.txt
adviewer.egg-info/requires.txt
adviewer.egg-info/top_level.txt
adviewer/tests/__init__.py
adviewer/tests/conftest.py
adviewer/tests/test_basic.py
adviewer/tests/test_discovery.py
docs/Makefile
docs/make.bat
docs/source/conf.py
docs/source/index.rst