Metadata-Version: 1.1
Name: adviewer
Version: 0.0.0
Summary: AreaDetector configurator and viewer
Home-page: https://github.com/pcdshub/adviewer
Author: SLAC National Accelerator Laboratory
Author-email: UNKNOWN
License: BSD
Platform: UNKNOWN
Classifier: Development Status :: 2 - Pre-Alpha
Classifier: Natural Language :: English
Classifier: Programming Language :: Python :: 3
